Backtest/diagram.cp312-win_amd64.pyd
Backtest/entryexitlogic.cp312-win_amd64.pyd
Backtest/formula.cp312-win_amd64.pyd
Backtest/model.cp312-win_amd64.pyd
Backtest/util.cp312-win_amd64.pyd
quantvibe_backtest-0.0.113.dist-info/METADATA
quantvibe_backtest-0.0.113.dist-info/WHEEL
quantvibe_backtest-0.0.113.dist-info/top_level.txt
quantvibe_backtest-0.0.113.dist-info/RECORD
