Metadata-Version: 2.4
Name: QuantVibe_Backtest
Version: 0.0.113
Summary: Python package for internal backtest
Author: Fang Kai Hock
Author-email: fkh714@gmail.com
Requires-Dist: matplotlib
Requires-Dist: seaborn
Requires-Dist: pandas
Requires-Dist: numpy
Dynamic: author
Dynamic: author-email
Dynamic: requires-dist
Dynamic: summary
